single_line/__init__.py
single_line-1.1.0.dist-info/METADATA
single_line-1.1.0.dist-info/WHEEL
single_line-1.1.0.dist-info/namespace_packages.txt
single_line-1.1.0.dist-info/top_level.txt
single_line-1.1.0.dist-info/zip-safe
single_line-1.1.0.dist-info/RECORD
