Metadata-Version: 2.1
Name: single-line
Version: 1.1.0
Summary: A context manager to facilitate printing messages to the same line
Home-page: https://github.com/soda480/single-line
Author: Emilio Reyes
Author-email: soda480@gmail.com
Maintainer: 
Maintainer-email: 
License: Apache License, Version 2.0
Classifier: Programming Language :: Python
Classifier: Programming Language :: Python :: 3.8
Classifier: Programming Language :: Python :: 3.9
Classifier: Programming Language :: Python :: 3.10
Classifier: Programming Language :: Python :: 3.11
Classifier: Programming Language :: Python :: 3.12
Requires-Dist: colorama
Requires-Dist: cursor
